test/__init__.py
test/test_access.py
test/test_baseprofile.py
test/test_dryrun_project.py
test/test_file_ops.py
test/test_globalcache.py
test/test_queue.py
test/test_security.py
test/test_singleton.py
test/test_url.py
webchecks/Project.py
webchecks/__init__.py
webchecks/config.py
webchecks/access/AccessHead.py
webchecks/access/Gateway.py
webchecks/access/RequestJS.py
webchecks/access/RequestNoJS.py
webchecks/access/RobotsFile.py
webchecks/access/__init__.py
webchecks/access/security.py
webchecks/archive/AccessNode.py
webchecks/archive/FileArchive.py
webchecks/archive/GlobalCache.py
webchecks/archive/__init__.py
webchecks/monitor/KeywordFinder.py
webchecks/monitor/Report.py
webchecks/monitor/__init__.py
webchecks/profiles/BaseProfile.py
webchecks/profiles/ProfileConstants.py
webchecks/profiles/__init__.py
webchecks/profiles/profileDB.py
webchecks/utils/Error.py
webchecks/utils/OptionsError.py
webchecks/utils/__init__.py
webchecks/utils/check.py
webchecks/utils/constants.py
webchecks/utils/file_ops.py
webchecks/utils/messaging.py
webchecks/utils/singleton.py
webchecks/utils/timedqueue.py
webchecks/utils/url.py
webchecks-0.1.3.dist-info/LICENSE
webchecks-0.1.3.dist-info/METADATA
webchecks-0.1.3.dist-info/WHEEL
webchecks-0.1.3.dist-info/top_level.txt
webchecks-0.1.3.dist-info/RECORD
