Metadata-Version: 2.1
Name: webchecks
Version: 0.1.3
Summary: WebChecks is a BSD-licensed web search and research tool in Python traversing a given set of domains. 
Author: CopperEagle
License: Copyright (c) WebChecks developers.
Project-URL: Homepage, https://github.com/CopperEagle/WebChecks
Keywords: websearch,analysis,automation,web
Classifier: License :: OSI Approved :: BSD License
Classifier: Programming Language :: Python
Classifier: Programming Language :: Python :: 3
Requires-Python: >=3.9
License-File: LICENSE
Requires-Dist: beautifulsoup4 ==4.12.2
Requires-Dist: bs4 ==0.0.1
Requires-Dist: python-dotenv ==1.0.0
Requires-Dist: requests ==2.32.0
Requires-Dist: selenium ==4.12.0
Requires-Dist: selenium-wire ==5.1.0
Requires-Dist: typing-extensions ==4.7.1
Requires-Dist: urllib3 ==2.2.2
Requires-Dist: webdriver-manager ==4.0.0
